.coveragerc
.gitignore
.lbox
.lbox.check
AUTHORS
COPYING
GPL-3
HACKING.md
MANIFEST.in
README.rst
charm.1
setup.cfg
setup.py
tox.ini
.github/ISSUE_TEMPLATE.md
.github/PULL_REQUEST_TEMPLATE.md
.github/workflows/tests.yml
charm_tools.egg-info/PKG-INFO
charm_tools.egg-info/SOURCES.txt
charm_tools.egg-info/dependency_links.txt
charm_tools.egg-info/entry_points.txt
charm_tools.egg-info/requires.txt
charm_tools.egg-info/top_level.txt
charmtools/VERSION
charmtools/__init__.py
charmtools/bundles.py
charmtools/charms.py
charmtools/cli.py
charmtools/create.py
charmtools/diff_match_patch.py
charmtools/fetchers.py
charmtools/linter.py
charmtools/proof.py
charmtools/pullsource.py
charmtools/repofinder.py
charmtools/test.py
charmtools/utils.py
charmtools/version.py
charmtools/build/__init__.py
charmtools/build/builder.py
charmtools/build/config.py
charmtools/build/errors.py
charmtools/build/fetchers.py
charmtools/build/inspector.py
charmtools/build/tactics.py
charmtools/generators/__init__.py
charmtools/generators/generator.py
charmtools/generators/prompt.py
charmtools/generators/template.py
charmtools/generators/utils.py
charmtools/templates/__init__.py
charmtools/templates/bash/__init__.py
charmtools/templates/bash/template.py
charmtools/templates/bash/files/README.md
charmtools/templates/bash/files/config.yaml
charmtools/templates/bash/files/icon.svg
charmtools/templates/bash/files/metadata.yaml
charmtools/templates/bash/files/revision
charmtools/templates/bash/files/hooks/config-changed
charmtools/templates/bash/files/hooks/install
charmtools/templates/bash/files/hooks/relation-name-relation-broken
charmtools/templates/bash/files/hooks/relation-name-relation-changed
charmtools/templates/bash/files/hooks/relation-name-relation-departed
charmtools/templates/bash/files/hooks/relation-name-relation-joined
charmtools/templates/bash/files/hooks/start
charmtools/templates/bash/files/hooks/stop
charmtools/templates/bash/files/hooks/upgrade-charm
charmtools/templates/charm/README.md
charmtools/templates/charm/icon.svg
charmtools/templates/powershell/__init__.py
charmtools/templates/powershell/template.py
charmtools/templates/python/__init__.py
charmtools/templates/python/template.py
